{
  "elements": [
    {
      "kind": "box",
      "wasm_offset": 0,
      "pointer": null,
      "source": "ui.wpp:x=20,y=30",
      "props": {
        "height": 50,
        "width": 100,
        "x": 20,
        "y": 30
      }
    },
    {
      "kind": "box",
      "wasm_offset": 30,
      "pointer": null,
      "source": "ui.wpp:x=150,y=30",
      "props": {
        "height": 60,
        "width": 80,
        "x": 150,
        "y": 30
      }
    },
    {
      "kind": "group",
      "wasm_offset": 0,
      "pointer": null,
      "source": null,
      "props": null
    }
  ]
}